common_utils/__init__.py
common_utils/apis/__init__.py
common_utils/apis/budget_baker.py
common_utils/apis/firebase.py
common_utils/apis/notion.py
common_utils/apis/ticktick/__init__.py
common_utils/apis/ticktick/cookies_login.py
common_utils/apis/ticktick/events.py
common_utils/apis/ticktick/focus.py
common_utils/apis/ticktick/habits.py
common_utils/apis/ticktick/tasks.py
common_utils/config.py
common_utils/distribution/pyinstaller.py
common_utils/logger.py
common_utils/py.typed
common_utils/time_utils.py
common_utils/tools/telegram.py
common_utils/web/__init__.py
common_utils/web/api_request.py
common_utils/web/cookies_handler.py
common_utils/web/oauth2_handler.py
common_utils/web/selenium.py
common_utils/windows/__init__.py
common_utils/windows/bluetooth.py
common_utils/windows/programs_windows.py
common_utils/windows/sound.py
my_common_utils-1.8.0.dist-info/METADATA
my_common_utils-1.8.0.dist-info/WHEEL
my_common_utils-1.8.0.dist-info/RECORD
