Metadata-Version: 2.3
Name: my-common-utils
Version: 1.8.0
Summary: A selection of common utility functions, and useful APIs
Author: Oliver Stoll
Author-email: oliverstoll.berlin@gmail.com
Requires-Python: >=3.12,<4.0
Classifier: Programming Language :: Python :: 3
Classifier: Programming Language :: Python :: 3.12
Classifier: Programming Language :: Python :: 3.13
Requires-Dist: authlib (>=1,<2)
Requires-Dist: cffi (>=1.17,<2.0)
Requires-Dist: flask (==3)
Requires-Dist: notion-client (>=2,<3)
Requires-Dist: pandas (>=2.3.1,<3.0.0)
Requires-Dist: psutil (>=7,<8)
Requires-Dist: pydantic (>=2,<3)
Requires-Dist: pygame (>=2,<3)
Requires-Dist: pytelegrambotapi (>=4,<5)
Requires-Dist: python-dotenv (>=1,<2)
Requires-Dist: pytz (>=2025.2,<2026.0)
Requires-Dist: pyyaml (>=6,<7)
Requires-Dist: selenium (>=4,<5)
Requires-Dist: spotipy (>=2,<3)
Requires-Dist: undetected-chromedriver (>=3,<4)
Requires-Dist: webdriver-manager (>=4,<5)
